{"1":{"str":"tests/testdata/serif_dog-bites-man.xml"},"2":{"rec":{"1":{"str":"a90d397a-560f-44a0-baae-c82a34e4be09"}}},"3":{"str":"CommunicationType.OTHER"},"4":{"str":"<DOC id=\"dog-bites-man\" type=\"other\">\n<HEADLINE>\nDog Bites Man\n</HEADLINE>\n<TEXT>\n<P>\nJohn Smith, manager of ACME INC, was bit by a dog on March 10th, 2013.\n</P>\n<P>\nHe died!\n</P>\n<P>\nJohn's daughter Mary expressed sorrow.\n</P>\n</TEXT>\n</DOC>\n"},"8":{"rec":{"1":{"str":"concrete_serif v3.10.1pre"},"2":{"i64":1421771999},"6":{"i32":1}}},"11":{"lst":["rec",4,{"1":{"rec":{"1":{"str":"e908e890-f917-406f-93ad-6d6481f929e5"}}},"2":{"lst":["rec",0]},"3":{"rec":{"1":{"i32":81},"2":{"i32":82}}},"5":{"str":"SectionKind.PASSAGE"}},{"1":{"rec":{"1":{"str":"bbf9c290-ee96-4ac4-a293-1fd3bf8c8693"}}},"2":{"lst":["rec",1,{"1":{"rec":{"1":{"str":"5947cfa3-2a43-4216-9d61-79c852df60c8"}}},"2":{"rec":{"1":{"rec":{"1":{"str":"195d4aa4-dcdf-45eb-b341-d67b36251a3e"}}},"2":{"rec":{"1":{"str":"Serif: tokens"},"2":{"i64":1421771999},"6":{"i32":1}}},"3":{"rec":{"1":{"lst":["rec",19,{"1":{"i32":0},"2":{"str":"John"},"3":{"rec":{"1":{"i32":86},"2":{"i32":90}}}},{"1":{"i32":1},"2":{"str":"Smith"},"3":{"rec":{"1":{"i32":91},"2":{"i32":96}}}},{"1":{"i32":2},"2":{"str":","},"3":{"rec":{"1":{"i32":96},"2":{"i32":97}}}},{"1":{"i32":3},"2":{"str":"manager"},"3":{"rec":{"1":{"i32":98},"2":{"i32":105}}}},{"1":{"i32":4},"2":{"str":"of"},"3":{"rec":{"1":{"i32":106},"2":{"i32":108}}}},{"1":{"i32":5},"2":{"str":"ACME"},"3":{"rec":{"1":{"i32":109},"2":{"i32":113}}}},{"1":{"i32":6},"2":{"str":"INC"},"3":{"rec":{"1":{"i32":114},"2":{"i32":117}}}},{"1":{"i32":7},"2":{"str":","},"3":{"rec":{"1":{"i32":117},"2":{"i32":118}}}},{"1":{"i32":8},"2":{"str":"was"},"3":{"rec":{"1":{"i32":119},"2":{"i32":122}}}},{"1":{"i32":9},"2":{"str":"bit"},"3":{"rec":{"1":{"i32":123},"2":{"i32":126}}}},{"1":{"i32":10},"2":{"str":"by"},"3":{"rec":{"1":{"i32":127},"2":{"i32":129}}}},{"1":{"i32":11},"2":{"str":"a"},"3":{"rec":{"1":{"i32":130},"2":{"i32":131}}}},{"1":{"i32":12},"2":{"str":"dog"},"3":{"rec":{"1":{"i32":132},"2":{"i32":135}}}},{"1":{"i32":13},"2":{"str":"on"},"3":{"rec":{"1":{"i32":136},"2":{"i32":138}}}},{"1":{"i32":14},"2":{"str":"March"},"3":{"rec":{"1":{"i32":139},"2":{"i32":144}}}},{"1":{"i32":15},"2":{"str":"10th"},"3":{"rec":{"1":{"i32":145},"2":{"i32":149}}}},{"1":{"i32":16},"2":{"str":","},"3":{"rec":{"1":{"i32":149},"2":{"i32":150}}}},{"1":{"i32":17},"2":{"str":"2013"},"3":{"rec":{"1":{"i32":151},"2":{"i32":155}}}},{"1":{"i32":18},"2":{"str":"."},"3":{"rec":{"1":{"i32":155},"2":{"i32":156}}}}]}}},"5":{"i32":1},"6":{"lst":["rec",2,{"1":{"rec":{"1":{"str":"e1ee0eef-e3e5-4f77-bfa4-31e0f057cc4d"}}},"2":{"rec":{"1":{"str":"Serif: part-of-speech"},"2":{"i64":1421771999},"6":{"i32":1}}},"3":{"lst":["rec",19,{"1":{"i32":0},"2":{"str":"NNP"}},{"1":{"i32":1},"2":{"str":"NNP"}},{"1":{"i32":2},"2":{"str":","}},{"1":{"i32":3},"2":{"str":"NN"}},{"1":{"i32":4},"2":{"str":"IN"}},{"1":{"i32":5},"2":{"str":"NNP"}},{"1":{"i32":6},"2":{"str":"NNP"}},{"1":{"i32":7},"2":{"str":","}},{"1":{"i32":8},"2":{"str":"VBD"}},{"1":{"i32":9},"2":{"str":"NN"}},{"1":{"i32":10},"2":{"str":"IN"}},{"1":{"i32":11},"2":{"str":"DT"}},{"1":{"i32":12},"2":{"str":"NN"}},{"1":{"i32":13},"2":{"str":"IN"}},{"1":{"i32":14},"2":{"str":"DATE-NNP"}},{"1":{"i32":15},"2":{"str":"JJ"}},{"1":{"i32":16},"2":{"str":","}},{"1":{"i32":17},"2":{"str":"CD"}},{"1":{"i32":18},"2":{"str":"."}}]},"4":{"str":"POS"}},{"1":{"rec":{"1":{"str":"00692343-f8e1-43e5-be99-64d2e957f0ba"}}},"2":{"rec":{"1":{"str":"Serif: names"},"2":{"i64":1421771999},"6":{"i32":1}}},"3":{"lst":["rec",19,{"1":{"i32":0},"2":{"str":"PER"},"3":{"dbl":1}},{"1":{"i32":1},"2":{"str":"PER"},"3":{"dbl":1}},{"1":{"i32":2},"2":{"str":"NONE"},"3":{"dbl":0}},{"1":{"i32":3},"2":{"str":"NONE"},"3":{"dbl":0}},{"1":{"i32":4},"2":{"str":"NONE"},"3":{"dbl":0}},{"1":{"i32":5},"2":{"str":"ORG"},"3":{"dbl":1}},{"1":{"i32":6},"2":{"str":"ORG"},"3":{"dbl":1}},{"1":{"i32":7},"2":{"str":"NONE"},"3":{"dbl":0}},{"1":{"i32":8},"2":{"str":"NONE"},"3":{"dbl":0}},{"1":{"i32":9},"2":{"str":"NONE"},"3":{"dbl":0}},{"1":{"i32":10},"2":{"str":"NONE"},"3":{"dbl":0}},{"1":{"i32":11},"2":{"str":"NONE"},"3":{"dbl":0}},{"1":{"i32":12},"2":{"str":"NONE"},"3":{"dbl":0}},{"1":{"i32":13},"2":{"str":"NONE"},"3":{"dbl":0}},{"1":{"i32":14},"2":{"str":"NONE"},"3":{"dbl":0}},{"1":{"i32":15},"2":{"str":"NONE"},"3":{"dbl":0}},{"1":{"i32":16},"2":{"str":"NONE"},"3":{"dbl":0}},{"1":{"i32":17},"2":{"str":"NONE"},"3":{"dbl":0}},{"1":{"i32":18},"2":{"str":"NONE"},"3":{"dbl":0}}]},"4":{"str":"NER"}}]},"7":{"lst":["rec",1,{"1":{"rec":{"1":{"str":"0c958ed4-7b62-4d0c-9921-b60b16b72457"}}},"2":{"rec":{"1":{"str":"Serif: parse"},"2":{"i64":1421771999},"6":{"i32":1}}},"3":{"lst":["rec",55,{"1":{"i32":0},"2":{"str":"S"},"3":{"lst":["i32",3,1,23,53]},"4":{"i32":-1}},{"1":{"i32":1},"2":{"str":"NP"},"3":{"lst":["i32",4,2,7,9,21]},"4":{"i32":-1}},{"1":{"i32":2},"2":{"str":"NPP"},"3":{"lst":["i32",2,3,5]},"4":{"i32":-1}},{"1":{"i32":3},"2":{"str":"NNP"},"3":{"lst":["i32",1,4]},"4":{"i32":-1}},{"1":{"i32":4},"2":{"str":"john"},"3":{"lst":["i32",0]},"4":{"i32":-1},"5":{"i32":0},"6":{"i32":1}},{"1":{"i32":5},"2":{"str":"NNP"},"3":{"lst":["i32",1,6]},"4":{"i32":-1}},{"1":{"i32":6},"2":{"str":"smith"},"3":{"lst":["i32",0]},"4":{"i32":-1},"5":{"i32":1},"6":{"i32":2}},{"1":{"i32":7},"2":{"str":","},"3":{"lst":["i32",1,8]},"4":{"i32":-1}},{"1":{"i32":8},"2":{"str":","},"3":{"lst":["i32",0]},"4":{"i32":-1},"5":{"i32":2},"6":{"i32":3}},{"1":{"i32":9},"2":{"str":"NP"},"3":{"lst":["i32",2,10,13]},"4":{"i32":-1}},{"1":{"i32":10},"2":{"str":"NPA"},"3":{"lst":["i32",1,11]},"4":{"i32":-1}},{"1":{"i32":11},"2":{"str":"NN"},"3":{"lst":["i32",1,12]},"4":{"i32":-1}},{"1":{"i32":12},"2":{"str":"manager"},"3":{"lst":["i32",0]},"4":{"i32":-1},"5":{"i32":3},"6":{"i32":4}},{"1":{"i32":13},"2":{"str":"PP"},"3":{"lst":["i32",2,14,16]},"4":{"i32":-1}},{"1":{"i32":14},"2":{"str":"IN"},"3":{"lst":["i32",1,15]},"4":{"i32":-1}},{"1":{"i32":15},"2":{"str":"of"},"3":{"lst":["i32",0]},"4":{"i32":-1},"5":{"i32":4},"6":{"i32":5}},{"1":{"i32":16},"2":{"str":"NPP"},"3":{"lst":["i32",2,17,19]},"4":{"i32":-1}},{"1":{"i32":17},"2":{"str":"NNP"},"3":{"lst":["i32",1,18]},"4":{"i32":-1}},{"1":{"i32":18},"2":{"str":"acme"},"3":{"lst":["i32",0]},"4":{"i32":-1},"5":{"i32":5},"6":{"i32":6}},{"1":{"i32":19},"2":{"str":"NNP"},"3":{"lst":["i32",1,20]},"4":{"i32":-1}},{"1":{"i32":20},"2":{"str":"inc"},"3":{"lst":["i32",0]},"4":{"i32":-1},"5":{"i32":6},"6":{"i32":7}},{"1":{"i32":21},"2":{"str":","},"3":{"lst":["i32",1,22]},"4":{"i32":-1}},{"1":{"i32":22},"2":{"str":","},"3":{"lst":["i32",0]},"4":{"i32":-1},"5":{"i32":7},"6":{"i32":8}},{"1":{"i32":23},"2":{"str":"VP"},"3":{"lst":["i32",2,24,26]},"4":{"i32":-1}},{"1":{"i32":24},"2":{"str":"VBD"},"3":{"lst":["i32",1,25]},"4":{"i32":-1}},{"1":{"i32":25},"2":{"str":"was"},"3":{"lst":["i32",0]},"4":{"i32":-1},"5":{"i32":8},"6":{"i32":9}},{"1":{"i32":26},"2":{"str":"NP"},"3":{"lst":["i32",2,27,30]},"4":{"i32":-1}},{"1":{"i32":27},"2":{"str":"NPA"},"3":{"lst":["i32",1,28]},"4":{"i32":-1}},{"1":{"i32":28},"2":{"str":"NN"},"3":{"lst":["i32",1,29]},"4":{"i32":-1}},{"1":{"i32":29},"2":{"str":"bit"},"3":{"lst":["i32",0]},"4":{"i32":-1},"5":{"i32":9},"6":{"i32":10}},{"1":{"i32":30},"2":{"str":"PP"},"3":{"lst":["i32",2,31,33]},"4":{"i32":-1}},{"1":{"i32":31},"2":{"str":"IN"},"3":{"lst":["i32",1,32]},"4":{"i32":-1}},{"1":{"i32":32},"2":{"str":"by"},"3":{"lst":["i32",0]},"4":{"i32":-1},"5":{"i32":10},"6":{"i32":11}},{"1":{"i32":33},"2":{"str":"NP"},"3":{"lst":["i32",2,34,39]},"4":{"i32":-1}},{"1":{"i32":34},"2":{"str":"NPA"},"3":{"lst":["i32",2,35,37]},"4":{"i32":-1}},{"1":{"i32":35},"2":{"str":"DT"},"3":{"lst":["i32",1,36]},"4":{"i32":-1}},{"1":{"i32":36},"2":{"str":"a"},"3":{"lst":["i32",0]},"4":{"i32":-1},"5":{"i32":11},"6":{"i32":12}},{"1":{"i32":37},"2":{"str":"NN"},"3":{"lst":["i32",1,38]},"4":{"i32":-1}},{"1":{"i32":38},"2":{"str":"dog"},"3":{"lst":["i32",0]},"4":{"i32":-1},"5":{"i32":12},"6":{"i32":13}},{"1":{"i32":39},"2":{"str":"PP"},"3":{"lst":["i32",2,40,42]},"4":{"i32":-1}},{"1":{"i32":40},"2":{"str":"IN"},"3":{"lst":["i32",1,41]},"4":{"i32":-1}},{"1":{"i32":41},"2":{"str":"on"},"3":{"lst":["i32",0]},"4":{"i32":-1},"5":{"i32":13},"6":{"i32":14}},{"1":{"i32":42},"2":{"str":"NP"},"3":{"lst":["i32",3,43,48,50]},"4":{"i32":-1}},{"1":{"i32":43},"2":{"str":"DATE"},"3":{"lst":["i32",2,44,46]},"4":{"i32":-1}},{"1":{"i32":44},"2":{"str":"DATE-NNP"},"3":{"lst":["i32",1,45]},"4":{"i32":-1}},{"1":{"i32":45},"2":{"str":"march"},"3":{"lst":["i32",0]},"4":{"i32":-1},"5":{"i32":14},"6":{"i32":15}},{"1":{"i32":46},"2":{"str":"JJ"},"3":{"lst":["i32",1,47]},"4":{"i32":-1}},{"1":{"i32":47},"2":{"str":"10th"},"3":{"lst":["i32",0]},"4":{"i32":-1},"5":{"i32":15},"6":{"i32":16}},{"1":{"i32":48},"2":{"str":","},"3":{"lst":["i32",1,49]},"4":{"i32":-1}},{"1":{"i32":49},"2":{"str":","},"3":{"lst":["i32",0]},"4":{"i32":-1},"5":{"i32":16},"6":{"i32":17}},{"1":{"i32":50},"2":{"str":"NPA"},"3":{"lst":["i32",1,51]},"4":{"i32":-1}},{"1":{"i32":51},"2":{"str":"CD"},"3":{"lst":["i32",1,52]},"4":{"i32":-1}},{"1":{"i32":52},"2":{"str":"2013"},"3":{"lst":["i32",0]},"4":{"i32":-1},"5":{"i32":17},"6":{"i32":18}},{"1":{"i32":53},"2":{"str":"."},"3":{"lst":["i32",1,54]},"4":{"i32":-1}},{"1":{"i32":54},"2":{"str":"."},"3":{"lst":["i32",0]},"4":{"i32":-1},"5":{"i32":18},"6":{"i32":19}}]}}]}}},"3":{"rec":{"1":{"i32":86},"2":{"i32":156}}}}]},"3":{"rec":{"1":{"i32":85},"2":{"i32":162}}},"5":{"str":"SectionKind.PASSAGE"}},{"1":{"rec":{"1":{"str":"3dd2bb68-7c5b-4a41-aa94-020a997aaad2"}}},"2":{"lst":["rec",1,{"1":{"rec":{"1":{"str":"74b8b16f-8ddf-4375-9e83-f92d8d599004"}}},"2":{"rec":{"1":{"rec":{"1":{"str":"f29f6378-cded-4fa4-a0b4-02c5cea39aa2"}}},"2":{"rec":{"1":{"str":"Serif: tokens"},"2":{"i64":1421771999},"6":{"i32":1}}},"3":{"rec":{"1":{"lst":["rec",3,{"1":{"i32":0},"2":{"str":"He"},"3":{"rec":{"1":{"i32":166},"2":{"i32":168}}}},{"1":{"i32":1},"2":{"str":"died"},"3":{"rec":{"1":{"i32":169},"2":{"i32":173}}}},{"1":{"i32":2},"2":{"str":"!"},"3":{"rec":{"1":{"i32":173},"2":{"i32":174}}}}]}}},"5":{"i32":1},"6":{"lst":["rec",2,{"1":{"rec":{"1":{"str":"cc27bc1f-302e-44f4-b681-39a6106c4a40"}}},"2":{"rec":{"1":{"str":"Serif: part-of-speech"},"2":{"i64":1421771999},"6":{"i32":1}}},"3":{"lst":["rec",3,{"1":{"i32":0},"2":{"str":"PRP"}},{"1":{"i32":1},"2":{"str":"VBD"}},{"1":{"i32":2},"2":{"str":"."}}]},"4":{"str":"POS"}},{"1":{"rec":{"1":{"str":"f1cb2f15-2881-4296-894b-58ab978e6a5d"}}},"2":{"rec":{"1":{"str":"Serif: names"},"2":{"i64":1421771999},"6":{"i32":1}}},"3":{"lst":["rec",3,{"1":{"i32":0},"2":{"str":"NONE"},"3":{"dbl":0}},{"1":{"i32":1},"2":{"str":"NONE"},"3":{"dbl":0}},{"1":{"i32":2},"2":{"str":"NONE"},"3":{"dbl":0}}]},"4":{"str":"NER"}}]},"7":{"lst":["rec",1,{"1":{"rec":{"1":{"str":"b365bb6d-a5eb-4dad-af1d-867e460e58f3"}}},"2":{"rec":{"1":{"str":"Serif: parse"},"2":{"i64":1421771999},"6":{"i32":1}}},"3":{"lst":["rec",9,{"1":{"i32":0},"2":{"str":"S"},"3":{"lst":["i32",3,1,4,7]},"4":{"i32":-1}},{"1":{"i32":1},"2":{"str":"NPA"},"3":{"lst":["i32",1,2]},"4":{"i32":-1}},{"1":{"i32":2},"2":{"str":"PRP"},"3":{"lst":["i32",1,3]},"4":{"i32":-1}},{"1":{"i32":3},"2":{"str":"he"},"3":{"lst":["i32",0]},"4":{"i32":-1},"5":{"i32":0},"6":{"i32":1}},{"1":{"i32":4},"2":{"str":"VP"},"3":{"lst":["i32",1,5]},"4":{"i32":-1}},{"1":{"i32":5},"2":{"str":"VBD"},"3":{"lst":["i32",1,6]},"4":{"i32":-1}},{"1":{"i32":6},"2":{"str":"died"},"3":{"lst":["i32",0]},"4":{"i32":-1},"5":{"i32":1},"6":{"i32":2}},{"1":{"i32":7},"2":{"str":"."},"3":{"lst":["i32",1,8]},"4":{"i32":-1}},{"1":{"i32":8},"2":{"str":"!"},"3":{"lst":["i32",0]},"4":{"i32":-1},"5":{"i32":2},"6":{"i32":3}}]}}]}}},"3":{"rec":{"1":{"i32":166},"2":{"i32":174}}}}]},"3":{"rec":{"1":{"i32":165},"2":{"i32":180}}},"5":{"str":"SectionKind.PASSAGE"}},{"1":{"rec":{"1":{"str":"b04c36d1-d2d0-425e-963d-e6a53ed359fe"}}},"2":{"lst":["rec",1,{"1":{"rec":{"1":{"str":"cf5178b1-850c-4b10-9f9a-55d5b76b6c0b"}}},"2":{"rec":{"1":{"rec":{"1":{"str":"52e59c5d-1d9b-4529-af5b-8a7ae6706b32"}}},"2":{"rec":{"1":{"str":"Serif: tokens"},"2":{"i64":1421771999},"6":{"i32":1}}},"3":{"rec":{"1":{"lst":["rec",7,{"1":{"i32":0},"2":{"str":"John"},"3":{"rec":{"1":{"i32":184},"2":{"i32":188}}}},{"1":{"i32":1},"2":{"str":"'s"},"3":{"rec":{"1":{"i32":188},"2":{"i32":190}}}},{"1":{"i32":2},"2":{"str":"daughter"},"3":{"rec":{"1":{"i32":191},"2":{"i32":199}}}},{"1":{"i32":3},"2":{"str":"Mary"},"3":{"rec":{"1":{"i32":200},"2":{"i32":204}}}},{"1":{"i32":4},"2":{"str":"expressed"},"3":{"rec":{"1":{"i32":205},"2":{"i32":214}}}},{"1":{"i32":5},"2":{"str":"sorrow"},"3":{"rec":{"1":{"i32":215},"2":{"i32":221}}}},{"1":{"i32":6},"2":{"str":"."},"3":{"rec":{"1":{"i32":221},"2":{"i32":222}}}}]}}},"5":{"i32":1},"6":{"lst":["rec",2,{"1":{"rec":{"1":{"str":"843f065b-7fec-4f4f-8c18-215ca2760fe6"}}},"2":{"rec":{"1":{"str":"Serif: part-of-speech"},"2":{"i64":1421771999},"6":{"i32":1}}},"3":{"lst":["rec",7,{"1":{"i32":0},"2":{"str":"NNP"}},{"1":{"i32":1},"2":{"str":"POS"}},{"1":{"i32":2},"2":{"str":"NN"}},{"1":{"i32":3},"2":{"str":"NNP"}},{"1":{"i32":4},"2":{"str":"VBD"}},{"1":{"i32":5},"2":{"str":"NN"}},{"1":{"i32":6},"2":{"str":"."}}]},"4":{"str":"POS"}},{"1":{"rec":{"1":{"str":"0785daa6-7824-499f-b8ce-cbb18f7ef1ba"}}},"2":{"rec":{"1":{"str":"Serif: names"},"2":{"i64":1421771999},"6":{"i32":1}}},"3":{"lst":["rec",7,{"1":{"i32":0},"2":{"str":"PER"},"3":{"dbl":1}},{"1":{"i32":1},"2":{"str":"NONE"},"3":{"dbl":0}},{"1":{"i32":2},"2":{"str":"NONE"},"3":{"dbl":0}},{"1":{"i32":3},"2":{"str":"PER"},"3":{"dbl":1}},{"1":{"i32":4},"2":{"str":"NONE"},"3":{"dbl":0}},{"1":{"i32":5},"2":{"str":"NONE"},"3":{"dbl":0}},{"1":{"i32":6},"2":{"str":"NONE"},"3":{"dbl":0}}]},"4":{"str":"NER"}}]},"7":{"lst":["rec",1,{"1":{"rec":{"1":{"str":"58a170c0-ad03-4132-97be-2b0db2419609"}}},"2":{"rec":{"1":{"str":"Serif: parse"},"2":{"i64":1421771999},"6":{"i32":1}}},"3":{"lst":["rec",21,{"1":{"i32":0},"2":{"str":"S"},"3":{"lst":["i32",3,1,13,19]},"4":{"i32":-1}},{"1":{"i32":1},"2":{"str":"NPA"},"3":{"lst":["i32",3,2,8,10]},"4":{"i32":-1}},{"1":{"i32":2},"2":{"str":"NPPOS"},"3":{"lst":["i32",2,3,6]},"4":{"i32":-1}},{"1":{"i32":3},"2":{"str":"NPP"},"3":{"lst":["i32",1,4]},"4":{"i32":-1}},{"1":{"i32":4},"2":{"str":"NNP"},"3":{"lst":["i32",1,5]},"4":{"i32":-1}},{"1":{"i32":5},"2":{"str":"john"},"3":{"lst":["i32",0]},"4":{"i32":-1},"5":{"i32":0},"6":{"i32":1}},{"1":{"i32":6},"2":{"str":"POS"},"3":{"lst":["i32",1,7]},"4":{"i32":-1}},{"1":{"i32":7},"2":{"str":"'s"},"3":{"lst":["i32",0]},"4":{"i32":-1},"5":{"i32":1},"6":{"i32":2}},{"1":{"i32":8},"2":{"str":"NN"},"3":{"lst":["i32",1,9]},"4":{"i32":-1}},{"1":{"i32":9},"2":{"str":"daughter"},"3":{"lst":["i32",0]},"4":{"i32":-1},"5":{"i32":2},"6":{"i32":3}},{"1":{"i32":10},"2":{"str":"NPP"},"3":{"lst":["i32",1,11]},"4":{"i32":-1}},{"1":{"i32":11},"2":{"str":"NNP"},"3":{"lst":["i32",1,12]},"4":{"i32":-1}},{"1":{"i32":12},"2":{"str":"mary"},"3":{"lst":["i32",0]},"4":{"i32":-1},"5":{"i32":3},"6":{"i32":4}},{"1":{"i32":13},"2":{"str":"VP"},"3":{"lst":["i32",2,14,16]},"4":{"i32":-1}},{"1":{"i32":14},"2":{"str":"VBD"},"3":{"lst":["i32",1,15]},"4":{"i32":-1}},{"1":{"i32":15},"2":{"str":"expressed"},"3":{"lst":["i32",0]},"4":{"i32":-1},"5":{"i32":4},"6":{"i32":5}},{"1":{"i32":16},"2":{"str":"NPA"},"3":{"lst":["i32",1,17]},"4":{"i32":-1}},{"1":{"i32":17},"2":{"str":"NN"},"3":{"lst":["i32",1,18]},"4":{"i32":-1}},{"1":{"i32":18},"2":{"str":"sorrow"},"3":{"lst":["i32",0]},"4":{"i32":-1},"5":{"i32":5},"6":{"i32":6}},{"1":{"i32":19},"2":{"str":"."},"3":{"lst":["i32",1,20]},"4":{"i32":-1}},{"1":{"i32":20},"2":{"str":"."},"3":{"lst":["i32",0]},"4":{"i32":-1},"5":{"i32":6},"6":{"i32":7}}]}}]}}},"3":{"rec":{"1":{"i32":184},"2":{"i32":222}}}}]},"3":{"rec":{"1":{"i32":183},"2":{"i32":228}}},"5":{"str":"SectionKind.PASSAGE"}}]},"12":{"lst":["rec",3,{"1":{"rec":{"1":{"str":"34dadb16-0f94-430d-8edd-0b49e9b37232"}}},"2":{"rec":{"1":{"str":"Serif: names"},"2":{"i64":1421771999},"6":{"i32":1}}},"3":{"lst":["rec",4,{"1":{"rec":{"1":{"str":"1835c872-979f-431f-bda0-6f984047bd2b"}}},"2":{"rec":{"1":{"lst":["i32",2,0,1]},"2":{"i32":-1},"3":{"rec":{"1":{"str":"195d4aa4-dcdf-45eb-b341-d67b36251a3e"}}},"4":{"rec":{"1":{"i32":86},"2":{"i32":96}}}}},"3":{"str":"PER"},"4":{"str":"PhraseType.NAME"},"6":{"str":"John Smith"}},{"1":{"rec":{"1":{"str":"b2f800aa-28c5-4114-a627-8086c0fb0ad2"}}},"2":{"rec":{"1":{"lst":["i32",2,5,6]},"2":{"i32":-1},"3":{"rec":{"1":{"str":"195d4aa4-dcdf-45eb-b341-d67b36251a3e"}}},"4":{"rec":{"1":{"i32":109},"2":{"i32":117}}}}},"3":{"str":"ORG"},"4":{"str":"PhraseType.NAME"},"6":{"str":"ACME INC"}},{"1":{"rec":{"1":{"str":"f48a8e7a-ea8f-4035-860f-659144c47b6d"}}},"2":{"rec":{"1":{"lst":["i32",1,0]},"2":{"i32":-1},"3":{"rec":{"1":{"str":"52e59c5d-1d9b-4529-af5b-8a7ae6706b32"}}},"4":{"rec":{"1":{"i32":184},"2":{"i32":188}}}}},"3":{"str":"PER"},"4":{"str":"PhraseType.NAME"},"6":{"str":"John"}},{"1":{"rec":{"1":{"str":"1cf3ae87-5f21-43b6-85fb-e5b0b03e542e"}}},"2":{"rec":{"1":{"lst":["i32",1,3]},"2":{"i32":-1},"3":{"rec":{"1":{"str":"52e59c5d-1d9b-4529-af5b-8a7ae6706b32"}}},"4":{"rec":{"1":{"i32":200},"2":{"i32":204}}}}},"3":{"str":"PER"},"4":{"str":"PhraseType.NAME"},"6":{"str":"Mary"}}]}},{"1":{"rec":{"1":{"str":"3560e780-afd5-4745-b007-53094b32a649"}}},"2":{"rec":{"1":{"str":"Serif: values"},"2":{"i64":1421771999},"6":{"i32":1}}},"3":{"lst":["rec",1,{"1":{"rec":{"1":{"str":"6a3a6528-74cb-4308-aa5e-5cff4a470bb1"}}},"2":{"rec":{"1":{"lst":["i32",4,14,15,16,17]},"2":{"i32":-1},"3":{"rec":{"1":{"str":"195d4aa4-dcdf-45eb-b341-d67b36251a3e"}}},"4":{"rec":{"1":{"i32":139},"2":{"i32":155}}}}},"3":{"str":"TIMEX2.TIME"},"4":{"str":"PhraseType.OTHER"},"6":{"str":"March 10th, 2013"}}]}},{"1":{"rec":{"1":{"str":"1d4f65f6-8909-4044-9564-3415279566a1"}}},"2":{"rec":{"1":{"str":"Serif: mentions"},"2":{"i64":1421771999},"6":{"i32":1}}},"3":{"lst":["rec",18,{"1":{"rec":{"1":{"str":"40dd1be3-affe-4fbe-a66f-02c6695856f5"}}},"2":{"rec":{"1":{"lst":["i32",8,0,1,2,3,4,5,6,7]},"2":{"i32":-1},"3":{"rec":{"1":{"str":"195d4aa4-dcdf-45eb-b341-d67b36251a3e"}}},"4":{"rec":{"1":{"i32":86},"2":{"i32":118}}}}},"3":{"str":"PER"},"4":{"str":"PhraseType.APPOSITIVE"},"6":{"str":"John Smith, manager of ACME INC,"},"7":{"lst":["rec",2,{"1":{"str":"ff5cb46b-6b60-424c-ac06-6cdf6ca692d6"}},{"1":{"str":"a79c94b8-e2d0-4be4-8f05-2858c65d5b36"}}]}},{"1":{"rec":{"1":{"str":"ff5cb46b-6b60-424c-ac06-6cdf6ca692d6"}}},"2":{"rec":{"1":{"lst":["i32",2,0,1]},"2":{"i32":-1},"3":{"rec":{"1":{"str":"195d4aa4-dcdf-45eb-b341-d67b36251a3e"}}},"4":{"rec":{"1":{"i32":86},"2":{"i32":96}}}}},"3":{"str":"PER"},"4":{"str":"PhraseType.NAME"},"6":{"str":"John Smith"},"7":{"lst":["rec",0]}},{"1":{"rec":{"1":{"str":"a79c94b8-e2d0-4be4-8f05-2858c65d5b36"}}},"2":{"rec":{"1":{"lst":["i32",4,3,4,5,6]},"2":{"i32":-1},"3":{"rec":{"1":{"str":"195d4aa4-dcdf-45eb-b341-d67b36251a3e"}}},"4":{"rec":{"1":{"i32":98},"2":{"i32":117}}}}},"3":{"str":"PER"},"4":{"str":"PhraseType.COMMON_NOUN"},"6":{"str":"manager of ACME INC"},"7":{"lst":["rec",0]}},{"1":{"rec":{"1":{"str":"ea4c1932-332e-4d38-9376-cbd45d82c4ff"}}},"2":{"rec":{"1":{"lst":["i32",1,3]},"2":{"i32":-1},"3":{"rec":{"1":{"str":"195d4aa4-dcdf-45eb-b341-d67b36251a3e"}}},"4":{"rec":{"1":{"i32":98},"2":{"i32":105}}}}},"3":{"str":"PER"},"4":{"str":"PhraseType.OTHER"},"6":{"str":"manager"},"7":{"lst":["rec",0]}},{"1":{"rec":{"1":{"str":"f630fb40-97bf-4376-9653-f12925d0b6bf"}}},"2":{"rec":{"1":{"lst":["i32",2,5,6]},"2":{"i32":-1},"3":{"rec":{"1":{"str":"195d4aa4-dcdf-45eb-b341-d67b36251a3e"}}},"4":{"rec":{"1":{"i32":109},"2":{"i32":117}}}}},"3":{"str":"ORG"},"4":{"str":"PhraseType.NAME"},"6":{"str":"ACME INC"},"7":{"lst":["rec",0]}},{"1":{"rec":{"1":{"str":"f9290f05-8af6-4836-a935-eab615675427"}}},"2":{"rec":{"1":{"lst":["i32",9,9,10,11,12,13,14,15,16,17]},"2":{"i32":-1},"3":{"rec":{"1":{"str":"195d4aa4-dcdf-45eb-b341-d67b36251a3e"}}},"4":{"rec":{"1":{"i32":123},"2":{"i32":155}}}}},"3":{"str":"OTH"},"4":{"str":"PhraseType.COMMON_NOUN"},"6":{"str":"bit by a dog on March 10th, 2013"},"7":{"lst":["rec",0]}},{"1":{"rec":{"1":{"str":"93f85810-9ca4-49d1-b981-c0c6b6ffbaa1"}}},"2":{"rec":{"1":{"lst":["i32",1,9]},"2":{"i32":-1},"3":{"rec":{"1":{"str":"195d4aa4-dcdf-45eb-b341-d67b36251a3e"}}},"4":{"rec":{"1":{"i32":123},"2":{"i32":126}}}}},"3":{"str":"OTH"},"4":{"str":"PhraseType.OTHER"},"6":{"str":"bit"},"7":{"lst":["rec",0]}},{"1":{"rec":{"1":{"str":"833f55ac-413d-40a4-a1e5-0a888ba471ae"}}},"2":{"rec":{"1":{"lst":["i32",7,11,12,13,14,15,16,17]},"2":{"i32":-1},"3":{"rec":{"1":{"str":"195d4aa4-dcdf-45eb-b341-d67b36251a3e"}}},"4":{"rec":{"1":{"i32":130},"2":{"i32":155}}}}},"3":{"str":"OTH"},"4":{"str":"PhraseType.COMMON_NOUN"},"6":{"str":"a dog on March 10th, 2013"},"7":{"lst":["rec",0]}},{"1":{"rec":{"1":{"str":"fd9aa3e9-1e64-4ea3-a42c-c40b4800551a"}}},"2":{"rec":{"1":{"lst":["i32",2,11,12]},"2":{"i32":-1},"3":{"rec":{"1":{"str":"195d4aa4-dcdf-45eb-b341-d67b36251a3e"}}},"4":{"rec":{"1":{"i32":130},"2":{"i32":135}}}}},"3":{"str":"OTH"},"4":{"str":"PhraseType.OTHER"},"6":{"str":"a dog"},"7":{"lst":["rec",0]}},{"1":{"rec":{"1":{"str":"d0ca6334-e74a-40c8-a92f-8e1a88656b03"}}},"2":{"rec":{"1":{"lst":["i32",4,14,15,16,17]},"2":{"i32":-1},"3":{"rec":{"1":{"str":"195d4aa4-dcdf-45eb-b341-d67b36251a3e"}}},"4":{"rec":{"1":{"i32":139},"2":{"i32":155}}}}},"3":{"str":"OTH"},"4":{"str":"PhraseType.APPOSITIVE"},"6":{"str":"March 10th, 2013"},"7":{"lst":["rec",2,{"1":{"str":"9e6d5431-2f4a-4b64-a357-41c58f5c20ef"}},{"1":{"str":"372769a8-bf09-4af3-904b-caff9067bfc7"}}]}},{"1":{"rec":{"1":{"str":"9e6d5431-2f4a-4b64-a357-41c58f5c20ef"}}},"2":{"rec":{"1":{"lst":["i32",2,14,15]},"2":{"i32":-1},"3":{"rec":{"1":{"str":"195d4aa4-dcdf-45eb-b341-d67b36251a3e"}}},"4":{"rec":{"1":{"i32":139},"2":{"i32":149}}}}},"3":{"str":"OTH"},"4":{"str":"PhraseType.COMMON_NOUN"},"6":{"str":"March 10th"},"7":{"lst":["rec",0]}},{"1":{"rec":{"1":{"str":"372769a8-bf09-4af3-904b-caff9067bfc7"}}},"2":{"rec":{"1":{"lst":["i32",1,17]},"2":{"i32":-1},"3":{"rec":{"1":{"str":"195d4aa4-dcdf-45eb-b341-d67b36251a3e"}}},"4":{"rec":{"1":{"i32":151},"2":{"i32":155}}}}},"3":{"str":"OTH"},"4":{"str":"PhraseType.COMMON_NOUN"},"6":{"str":"2013"},"7":{"lst":["rec",0]}},{"1":{"rec":{"1":{"str":"efe1c1d4-307d-4e36-95c9-7521870c6815"}}},"2":{"rec":{"1":{"lst":["i32",1,0]},"2":{"i32":-1},"3":{"rec":{"1":{"str":"f29f6378-cded-4fa4-a0b4-02c5cea39aa2"}}},"4":{"rec":{"1":{"i32":166},"2":{"i32":168}}}}},"3":{"str":"PER"},"4":{"str":"PhraseType.PRONOUN"},"6":{"str":"He"},"7":{"lst":["rec",0]}},{"1":{"rec":{"1":{"str":"d378d184-794d-4a3d-aacb-cfa59c4c92cf"}}},"2":{"rec":{"1":{"lst":["i32",4,0,1,2,3]},"2":{"i32":-1},"3":{"rec":{"1":{"str":"52e59c5d-1d9b-4529-af5b-8a7ae6706b32"}}},"4":{"rec":{"1":{"i32":184},"2":{"i32":204}}}}},"3":{"str":"PER.Individual"},"4":{"str":"PhraseType.NAME"},"6":{"str":"John's daughter Mary"},"7":{"lst":["rec",1,{"1":{"str":"2de64f9c-4b65-4fa4-9cbd-a419e82788e1"}}]}},{"1":{"rec":{"1":{"str":"ea5f3f13-93fa-4113-adae-e466544e8190"}}},"2":{"rec":{"1":{"lst":["i32",1,0]},"2":{"i32":-1},"3":{"rec":{"1":{"str":"52e59c5d-1d9b-4529-af5b-8a7ae6706b32"}}},"4":{"rec":{"1":{"i32":184},"2":{"i32":188}}}}},"3":{"str":"PER.Individual"},"4":{"str":"PhraseType.NAME"},"6":{"str":"John"},"7":{"lst":["rec",0]}},{"1":{"rec":{"1":{"str":"3e9d7137-94f6-43ff-80ee-c26bd30472c0"}}},"2":{"rec":{"1":{"lst":["i32",1,2]},"2":{"i32":-1},"3":{"rec":{"1":{"str":"52e59c5d-1d9b-4529-af5b-8a7ae6706b32"}}},"4":{"rec":{"1":{"i32":191},"2":{"i32":199}}}}},"3":{"str":"PER"},"4":{"str":"PhraseType.COMMON_NOUN"},"6":{"str":"daughter"},"7":{"lst":["rec",0]}},{"1":{"rec":{"1":{"str":"2de64f9c-4b65-4fa4-9cbd-a419e82788e1"}}},"2":{"rec":{"1":{"lst":["i32",1,3]},"2":{"i32":-1},"3":{"rec":{"1":{"str":"52e59c5d-1d9b-4529-af5b-8a7ae6706b32"}}},"4":{"rec":{"1":{"i32":200},"2":{"i32":204}}}}},"3":{"str":"PER"},"4":{"str":"PhraseType.OTHER"},"6":{"str":"Mary"},"7":{"lst":["rec",0]}},{"1":{"rec":{"1":{"str":"96f8efd8-0976-4a7f-8f47-e5e52459afc6"}}},"2":{"rec":{"1":{"lst":["i32",1,5]},"2":{"i32":-1},"3":{"rec":{"1":{"str":"52e59c5d-1d9b-4529-af5b-8a7ae6706b32"}}},"4":{"rec":{"1":{"i32":215},"2":{"i32":221}}}}},"3":{"str":"OTH"},"4":{"str":"PhraseType.COMMON_NOUN"},"6":{"str":"sorrow"},"7":{"lst":["rec",0]}}]}}]},"13":{"lst":["rec",2,{"1":{"rec":{"1":{"str":"36615845-9915-4f9f-b1a4-ae96b58c467c"}}},"2":{"rec":{"1":{"str":"Serif: doc-entities"},"2":{"i64":1421771999},"6":{"i32":1}}},"3":{"lst":["rec",3,{"1":{"rec":{"1":{"str":"c8d79e89-3b21-4c88-9b28-13b0202871e1"}}},"2":{"lst":["rec",5,{"1":{"str":"ff5cb46b-6b60-424c-ac06-6cdf6ca692d6"}},{"1":{"str":"40dd1be3-affe-4fbe-a66f-02c6695856f5"}},{"1":{"str":"a79c94b8-e2d0-4be4-8f05-2858c65d5b36"}},{"1":{"str":"efe1c1d4-307d-4e36-95c9-7521870c6815"}},{"1":{"str":"ea5f3f13-93fa-4113-adae-e466544e8190"}}]},"3":{"str":"PER.Individual"}},{"1":{"rec":{"1":{"str":"3c2c5b45-e356-4fb8-be9a-85bb42ac49a7"}}},"2":{"lst":["rec",1,{"1":{"str":"f630fb40-97bf-4376-9653-f12925d0b6bf"}}]},"3":{"str":"ORG.Commercial"}},{"1":{"rec":{"1":{"str":"e7071ef7-5874-4dc4-a8cb-c6697b63356b"}}},"2":{"lst":["rec",2,{"1":{"str":"d378d184-794d-4a3d-aacb-cfa59c4c92cf"}},{"1":{"str":"3e9d7137-94f6-43ff-80ee-c26bd30472c0"}}]},"3":{"str":"PER.Individual"}}]}},{"1":{"rec":{"1":{"str":"9ae21813-1c8a-4772-8a12-ea0286564aa1"}}},"2":{"rec":{"1":{"str":"Serif: doc-values"},"2":{"i64":1421771999},"6":{"i32":1}}},"3":{"lst":["rec",1,{"1":{"rec":{"1":{"str":"964bf065-edab-4db4-9005-9b2b1962912c"}}},"2":{"lst":["rec",1,{"1":{"str":"6a3a6528-74cb-4308-aa5e-5cff4a470bb1"}}]},"3":{"str":"TIMEX2.TIME"},"5":{"str":"2013-03-10"}}]}}]},"14":{"lst":["rec",2,{"1":{"rec":{"1":{"str":"1d04a557-ee20-4d99-944c-4793a6f6e0ad"}}},"2":{"rec":{"1":{"str":"Serif: relations"},"2":{"i64":1421771999},"6":{"i32":1}}},"3":{"lst":["rec",2,{"1":{"rec":{"1":{"str":"4aec9afc-f5bd-446e-ae32-db6e4d58baa5"}}},"3":{"str":"ORG-AFF.Employment"},"4":{"lst":["rec",2,{"1":{"str":"Role.RELATION_SOURCE_ROLE"},"2":{"rec":{"1":{"str":"a79c94b8-e2d0-4be4-8f05-2858c65d5b36"}}}},{"1":{"str":"Role.RELATION_TARGET_ROLE"},"2":{"rec":{"1":{"str":"f630fb40-97bf-4376-9653-f12925d0b6bf"}}}}]}},{"1":{"rec":{"1":{"str":"3ed27a2d-ffae-4f42-9129-4868b9765fac"}}},"3":{"str":"PER-SOC.Family"},"4":{"lst":["rec",2,{"1":{"str":"Role.RELATION_SOURCE_ROLE"},"2":{"rec":{"1":{"str":"ea5f3f13-93fa-4113-adae-e466544e8190"}}}},{"1":{"str":"Role.RELATION_TARGET_ROLE"},"2":{"rec":{"1":{"str":"3e9d7137-94f6-43ff-80ee-c26bd30472c0"}}}}]}}]}},{"1":{"rec":{"1":{"str":"df87bc00-7467-458d-8c26-66affd88e640"}}},"2":{"rec":{"1":{"str":"Serif: events"},"2":{"i64":1421771999},"6":{"i32":1}}},"3":{"lst":["rec",1,{"1":{"rec":{"1":{"str":"943bdd89-f801-427a-b498-4d99d7ed5c3d"}}},"2":{"str":"died"},"3":{"str":"Life.Die"},"4":{"lst":["rec",1,{"1":{"str":"Victim"},"2":{"rec":{"1":{"str":"efe1c1d4-307d-4e36-95c9-7521870c6815"}}}}]},"150":{"rec":{"1":{"lst":["i32",1,1]},"2":{"i32":-1},"3":{"rec":{"1":{"str":"f29f6378-cded-4fa4-a0b4-02c5cea39aa2"}}}}}}]}}]},"15":{"lst":["rec",2,{"1":{"rec":{"1":{"str":"e8ef0514-106e-47ba-b18f-98c1163bdc5d"}}},"2":{"rec":{"1":{"str":"Serif: relations"},"2":{"i64":1421771999},"6":{"i32":1}}},"3":{"lst":["rec",0]}},{"1":{"rec":{"1":{"str":"0ccf9b9a-50b5-4766-98b2-4d3a420a3ed5"}}},"2":{"rec":{"1":{"str":"Serif: events"},"2":{"i64":1421771999},"6":{"i32":1}}},"3":{"lst":["rec",1,{"1":{"rec":{"1":{"str":"c413534f-c569-40fb-8c0b-94625f1bd047"}}},"2":{"str":"Life.Die"},"3":{"lst":["rec",1,{"1":{"str":"Victim"},"2":{"rec":{"1":{"str":"c8d79e89-3b21-4c88-9b28-13b0202871e1"}}}}]},"5":{"lst":["rec",1,{"1":{"str":"JustificationType.DIRECT_MENTION"},"2":{"rec":{"1":{"str":"943bdd89-f801-427a-b498-4d99d7ed5c3d"}}}}]}}]}}]}}